forager_forward/__init__.py
forager_forward/app_clients/__init__.py
forager_forward/app_clients/base.py
forager_forward/app_clients/client.py
forager_forward/app_clients/email_client.py
forager_forward/app_services/__init__.py
forager_forward/app_services/email_validation_service.py
forager_forward/client_initializer.py
forager_forward/common/__init__.py
forager_forward/common/common_utilities.py
forager_forward/common/exceptions.py
forager_forward/common/project_types.py
forager_forward/common/storage.py
forager_forward/common/validators.py
forager_forward-0.1.1.dist-info/LICENSE
forager_forward-0.1.1.dist-info/METADATA
forager_forward-0.1.1.dist-info/WHEEL
forager_forward-0.1.1.dist-info/RECORD
