Metadata-Version: 2.1
Name: forager-forward
Version: 0.1.1
Summary: Hunter.io v2 api implementation
Home-page: https://github.com/victor-nuzhniy/forager.git
Author: victro-nuzhniy
Author-email: nuzhniyva@gmail.com
Requires-Python: >=3.10,<4.0
Classifier: Programming Language :: Python :: 3
Classifier: Programming Language :: Python :: 3.10
Classifier: Programming Language :: Python :: 3.11
Requires-Dist: httpx (>=0.26.0,<0.27.0)
Project-URL: Repository, https://github.com/victor-nuzhniy/forager.git
